{
  "frames": {
    "full": {
      "frame": {
        "x": 4,
        "y": 4,
        "w": 209,
        "h": 50
      },
      "rotated": false,
      "trimmed": true,
      "spriteSourceSize": {
        "x": 1,
        "y": 1,
        "w": 209,
        "h": 50
      },
      "sourceSize": {
        "w": 212,
        "h": 52
      },
      "pivot": {
        "x": 0.5,
        "y": 0.5
      }
    },
    "body": {
      "frame": {
        "x": 4,
        "y": 62,
        "w": 149,
        "h": 50
      },
      "rotated": false,
      "trimmed": true,
      "spriteSourceSize": {
        "x": 1,
        "y": 1,
        "w": 149,
        "h": 50
      },
      "sourceSize": {
        "w": 212,
        "h": 52
      },
      "pivot": {
        "x": 0.5,
        "y": 0.5
      }
    },
    "head": {
      "frame": {
        "x": 161,
        "y": 62,
        "w": 79,
        "h": 34
      },
      "rotated": false,
      "trimmed": true,
      "spriteSourceSize": {
        "x": 131,
        "y": 9,
        "w": 79,
        "h": 34
      },
      "sourceSize": {
        "w": 212,
        "h": 52
      },
      "pivot": {
        "x": 0.5,
        "y": 0.5
      }
    }
  },
  "meta": {
    "app": "http://free-tex-packer.com",
    "version": "0.6.7",
    "image": "launch-vehicle.png",
    "format": "RGBA8888",
    "size": {
      "w": 244,
      "h": 116
    },
    "scale": 1
  }
}